<?xml version="1.0" encoding="UTF-8"?>
<tags xmlns:TEI="http://www.tei-c.org/ns/1.0"
      xmlns:xhtml="http://www.w3.org/1999/xhtml"
      xmlns:xs="http://www.w3.org/2001/XMLSchema"
      xmlns:a18="http://sub.uni-goettingen.de/DB/ENT/projects/archaeo18/xslt"
      xmlns:ropen="http://ropen.sub.uni-goettingen.de/ropen-backend/xslt"
      xmlns:xd="http://www.oxygenxml.com/ns/doc/xsl"
      xmlns="http://www.w3.org/1999/xhtml">
   <tag>
      <tag>Petrarca, Francesco</tag>
      <facet>tei:persName</facet>
      <link>http://thesaurus.cerl.org/cgi-bin/record.pl?rid=cnp01259401</link>
      <count>2</count>
      <nodes>
         <persName xmlns="http://www.tei-c.org/ns/1.0"
                   ref="#CerlID:cnp01259401"
                   key="#PND:118593234 118593234">Petrarkas<addName type="display">Petrarca, Francesco</addName>
            <addName>Francesco Petrarca</addName>
            <addName>Francescho Petrarcha</addName>
            <addName>Francesco</addName>
            <addName>Francesco Petrarcha</addName>
            <addName>Franciscus Petrarca</addName>
            <addName>Franciscus</addName>
            <addName>Franciscus Petrarcha</addName>
            <addName>F P.</addName>
            <addName>P.</addName>
            <addName>F. P.</addName>
            <addName>Franciscus Petarcha</addName>
            <addName>Petarcha</addName>
            <addName>Petracca</addName>
            <addName>Francesco Petracco</addName>
            <addName>Petracco</addName>
            <addName>Franciscus Petracha</addName>
            <addName>Petracha</addName>
            <addName>Petrarca</addName>
            <addName>F Petrarca</addName>
            <addName>Petrarca, Francesco 1304-1374</addName>
            <addName>Francisco Petrarca</addName>
            <addName>Francoys Petrarca</addName>
            <addName>Franz Petrarca</addName>
            <addName>Petrarca Pseudo-</addName>
            <addName>Francisci Petrarce</addName>
            <addName>Petrarce</addName>
            <addName>Petrarch</addName>
            <addName>Petrarch</addName>
            <addName>Francesco Petrarch</addName>
            <addName>Francis Petrarch</addName>
            <addName>Petrarcha</addName>
            <addName>F Petrarcha</addName>
            <addName>Francisco Petrarcha</addName>
            <addName>Franczyssek Petrarcha</addName>
            <addName>Francesco Petrarche</addName>
            <addName>Petrarche</addName>
            <addName>Francisco Petrarche</addName>
            <addName>Franciscus Petrarche</addName>
            <addName>Franciscus Petrarchus</addName>
            <addName>Petrarchus</addName>
            <addName>Frances Petrarcke</addName>
            <addName>Petrarcke</addName>
            <addName>Fraunces Petrarcke</addName>
            <addName>Francoys Petrarcque</addName>
            <addName>Petrarcque</addName>
            <addName>Petrark</addName>
            <addName>Petrarka</addName>
            <addName>Petrarka</addName>
            <addName>France Petrarka</addName>
            <addName>Francesco Petrarka</addName>
            <addName>Franz Petrarka</addName>
            <addName>Frančesko Petrarka</addName>
            <addName>Francoys Petrarque</addName>
            <addName>Petrarque</addName>
            <addName>Franco̧ys Pétracque</addName>
            <addName>Pétracque</addName>
            <addName>Pseudo-Petrarca</addName>
            <addName>Pètrarque</addName>
            <addName>Francesco Pètrarque</addName>
            <addName>François Pètrarque</addName>
            <addName>Françoys Pétracque</addName>
            <addName>Pétracque</addName>
            <addName>Pétrarque</addName>
            <addName>Pétrarque</addName>
            <addName>Francesco Pétrarque</addName>
            <addName>François Pétrarque</addName>
         </persName>
      </nodes>
   </tag>
</tags>
