<?xml version="1.0" encoding="UTF-8"?>
<tags xmlns:TEI="http://www.tei-c.org/ns/1.0"
      xmlns:xhtml="http://www.w3.org/1999/xhtml"
      xmlns:xs="http://www.w3.org/2001/XMLSchema"
      xmlns:a18="http://sub.uni-goettingen.de/DB/ENT/projects/archaeo18/xslt"
      xmlns:ropen="http://ropen.sub.uni-goettingen.de/ropen-backend/xslt"
      xmlns:xd="http://www.oxygenxml.com/ns/doc/xsl"
      xmlns="http://www.w3.org/1999/xhtml">
   <tag>
      <tag>Pio Clem. 1. 51.</tag>
      <facet>tei:bibl</facet>
      <link>http://digi.ub.uni-heidelberg.de/diglit/visconti1782bd1/0165</link>
      <count>4</count>
      <nodes>
         <bibl xmlns="http://www.tei-c.org/ns/1.0">
            <ref target="#http://digi.ub.uni-heidelberg.de/diglit/visconti1782bd1/0165">
               <term ref="#http://arachne.uni-koeln.de/item/objekt/130427">Pio Clem. 1. 51</term>.</ref>
         </bibl>
      </nodes>
   </tag>
   <tag>
      <tag>Marbre de Dresde 54.154.154?</tag>
      <facet>tei:bibl</facet>
      <link>http://digi.ub.uni-heidelberg.de/diglit/leplat1733/0158</link>
      <count>2</count>
      <nodes>
         <bibl xmlns="http://www.tei-c.org/ns/1.0">
            <ref target="#http://digi.ub.uni-heidelberg.de/diglit/leplat1733/0158">Marbre de Dresde 54.154.154?</ref>
         </bibl>
      </nodes>
   </tag>
   <tag>
      <tag>thesaur. Brand. p. 161.266.266?</tag>
      <facet>tei:bibl</facet>
      <link>http://digi.ub.uni-heidelberg.de/diglit/beger1791bd3/0293</link>
      <count>2</count>
      <nodes>
         <bibl xmlns="http://www.tei-c.org/ns/1.0">
            <ref target="#http://digi.ub.uni-heidelberg.de/diglit/beger1791bd3/0293">thesaur.
                                        Brand. p. 161.266.266?</ref>
         </bibl>
      </nodes>
   </tag>
</tags>
