<?xml version="1.0" encoding="UTF-8"?>
<tags xmlns:TEI="http://www.tei-c.org/ns/1.0"
      xmlns:xhtml="http://www.w3.org/1999/xhtml"
      xmlns:xs="http://www.w3.org/2001/XMLSchema"
      xmlns:a18="http://sub.uni-goettingen.de/DB/ENT/projects/archaeo18/xslt"
      xmlns:ropen="http://ropen.sub.uni-goettingen.de/ropen-backend/xslt"
      xmlns:xd="http://www.oxygenxml.com/ns/doc/xsl"
      xmlns="http://www.w3.org/1999/xhtml">
   <tag>
      <tag/>
      <facet>tei:term</facet>
      <link>http://arachne.uni-koeln.de/item/objekt/14755 http://arachne.uni-koeln.de/item/objekt/14758</link>
      <count>2</count>
      <nodes>
         <term xmlns="http://www.tei-c.org/ns/1.0"
               ref="#http://arachne.uni-koeln.de/item/objekt/14755 #http://arachne.uni-koeln.de/item/objekt/14758">Eine Gruppe von zweyen Geniis</term>
      </nodes>
   </tag>
   <tag>
      <tag>Palazzo Borghesehor- ti Salustii</tag>
      <facet>tei:term</facet>
      <link>CensusID:10036302 http://arachne.uni-koeln.de/item/objekt/14733</link>
      <count>2</count>
      <nodes>
         <term xmlns="http://www.tei-c.org/ns/1.0"
               ref="#CensusID:10036302 #http://arachne.uni-koeln.de/item/objekt/14733">XXIII. Harmaphroditus. Im <term ref="#http://arachne.uni-koeln.de/item/sammlungen/1000238">Palazzo Borghese</term> gefunden, wo die <term ref="#http://arachne.uni-koeln.de/item/topographie/8004518">hor- 
                     ti Salustii</term>
         </term>
      </nodes>
   </tag>
   <tag>
      <tag/>
      <facet>tei:term</facet>
      <link>http://arachne.uni-koeln.de/item/sammlungen/1000238</link>
      <count>2</count>
      <nodes>
         <term xmlns="http://www.tei-c.org/ns/1.0"
               ref="#http://arachne.uni-koeln.de/item/sammlungen/1000238">Palazzo Borghese</term>
      </nodes>
   </tag>
   <tag>
      <tag/>
      <facet>tei:term</facet>
      <link>http://arachne.uni-koeln.de/item/topographie/8004518</link>
      <count>2</count>
      <nodes>
         <term xmlns="http://www.tei-c.org/ns/1.0"
               ref="#http://arachne.uni-koeln.de/item/topographie/8004518">hor- 
                     ti Salustii</term>
      </nodes>
   </tag>
   <tag>
      <tag/>
      <facet>tei:term</facet>
      <link>CensusID:10036341 http://arachne.uni-koeln.de/item/objekt/5816</link>
      <count>2</count>
      <nodes>
         <term xmlns="http://www.tei-c.org/ns/1.0"
               ref="#CensusID:10036341 #http://arachne.uni-koeln.de/item/objekt/5816">ein anderer</term>
      </nodes>
   </tag>
   <tag>
      <tag/>
      <facet>tei:term</facet>
      <link>http://arachne.uni-koeln.de/item/objekt/17837</link>
      <count>2</count>
      <nodes>
         <term xmlns="http://www.tei-c.org/ns/1.0"
               ref="#http://arachne.uni-koeln.de/item/objekt/17837">21.</term>
      </nodes>
   </tag>
   <tag>
      <tag/>
      <facet>tei:term</facet>
      <link/>
      <count>2</count>
      <nodes>
         <term xmlns="http://www.tei-c.org/ns/1.0"
               ref="#placeholder-file:/home/ingop/repo/archaeo18/./content/app/tei-pages/weimar-hs-2056-121.tei.xml-d19439e255">hermaphrodit mit allen attributen
                         der Dichtkunst</term>
      </nodes>
   </tag>
   <tag>
      <tag/>
      <facet>tei:term</facet>
      <link/>
      <count>2</count>
      <nodes>
         <term xmlns="http://www.tei-c.org/ns/1.0"
               ref="#placeholder-file:/home/ingop/repo/archaeo18/./content/app/tei-pages/weimar-hs-2056-121.tei.xml-d19439e266"
               type="collection">Mediceischen 
                     Gärten.</term>
      </nodes>
   </tag>
   <tag>
      <tag>Villa Albini</tag>
      <facet>tei:term</facet>
      <link>http://arachne.uni-koeln.de/item/objekt/27528</link>
      <count>2</count>
      <nodes>
         <term xmlns="http://www.tei-c.org/ns/1.0"
               ref="#http://arachne.uni-koeln.de/item/objekt/27528">Ein Anderer in <term ref="#http://arachne.uni-koeln.de/item/sammlungen/1000297">Villa Albini</term>
         </term>
      </nodes>
   </tag>
   <tag>
      <tag/>
      <facet>tei:term</facet>
      <link>http://arachne.uni-koeln.de/item/sammlungen/1000297</link>
      <count>2</count>
      <nodes>
         <term xmlns="http://www.tei-c.org/ns/1.0"
               ref="#http://arachne.uni-koeln.de/item/sammlungen/1000297">Villa Albini</term>
      </nodes>
   </tag>
   <tag>
      <tag/>
      <facet>tei:term</facet>
      <link>CensusID:156193 http://arachne.uni-koeln.de/item/gruppen/400570 http://arachne.uni-koeln.de/item/objekt/13426 http://arachne.uni-koeln.de/item/objekt/13427 http://arachne.uni-koeln.de/item/objekt/13428 http://arachne.uni-koeln.de/item/objekt/13429 http://arachne.uni-koeln.de/item/objekt/13430 http://arachne.uni-koeln.de/item/objekt/40491</link>
      <count>2</count>
      <nodes>
         <term xmlns="http://www.tei-c.org/ns/1.0"
               ref="#CensusID:156193 #http://arachne.uni-koeln.de/item/gruppen/400570 #http://arachne.uni-koeln.de/item/objekt/13426 #http://arachne.uni-koeln.de/item/objekt/13427 #http://arachne.uni-koeln.de/item/objekt/13428 #http://arachne.uni-koeln.de/item/objekt/13429 #http://arachne.uni-koeln.de/item/objekt/13430 #http://arachne.uni-koeln.de/item/objekt/40491">Il Toro Farnase</term>
      </nodes>
   </tag>
   <tag>
      <tag>Antiope (von Theben)</tag>
      <facet>tei:term</facet>
      <link>http://arachne.uni-koeln.de/item/objekt/13429</link>
      <count>2</count>
      <nodes>
         <term xmlns="http://www.tei-c.org/ns/1.0"
               ref="#http://arachne.uni-koeln.de/item/objekt/13429">
            <persName ref="#CerlID:cnp00824849" key="#PND:131746782">Antiope<addName type="display">Antiope (von Theben)</addName>
            </persName>
         </term>
      </nodes>
   </tag>
   <tag>
      <tag>Lykos</tag>
      <facet>tei:term</facet>
      <link>http://arachne.uni-koeln.de/item/objekt/13427</link>
      <count>2</count>
      <nodes>
         <term xmlns="http://www.tei-c.org/ns/1.0"
               ref="#http://arachne.uni-koeln.de/item/objekt/13427">
            <persName ref="#CerlID:cnp01300332">Lycas<addName type="display">Lykos</addName>
               <addName>Lycus</addName>
            </persName>
         </term>
      </nodes>
   </tag>
</tags>
