<?xml version="1.0" encoding="UTF-8"?>
<tags xmlns:TEI="http://www.tei-c.org/ns/1.0"
      xmlns:xhtml="http://www.w3.org/1999/xhtml"
      xmlns:xs="http://www.w3.org/2001/XMLSchema"
      xmlns:a18="http://sub.uni-goettingen.de/DB/ENT/projects/archaeo18/xslt"
      xmlns:ropen="http://ropen.sub.uni-goettingen.de/ropen-backend/xslt"
      xmlns:xd="http://www.oxygenxml.com/ns/doc/xsl"
      xmlns="http://www.w3.org/1999/xhtml">
   <tag>
      <tag>Campidoglio</tag>
      <facet>tei:term</facet>
      <link>http://arachne.uni-koeln.de/item/objekt/15955</link>
      <count>2</count>
      <nodes>
         <term xmlns="http://www.tei-c.org/ns/1.0"
               ref="#http://arachne.uni-koeln.de/item/objekt/15955">Von der im <term ref="#http://arachne.uni-koeln.de/item/sammlungen/1000358">Campidoglio</term>
         </term>
      </nodes>
   </tag>
   <tag>
      <tag/>
      <facet>tei:term</facet>
      <link>http://arachne.uni-koeln.de/item/sammlungen/1000358</link>
      <count>2</count>
      <nodes>
         <term xmlns="http://www.tei-c.org/ns/1.0"
               ref="#http://arachne.uni-koeln.de/item/sammlungen/1000358">Campidoglio</term>
      </nodes>
   </tag>
   <tag>
      <tag/>
      <facet>tei:term</facet>
      <link>CensusID:10034893 http://arachne.uni-koeln.de/item/objekt/15946</link>
      <count>2</count>
      <nodes>
         <term xmlns="http://www.tei-c.org/ns/1.0"
               ref="#CensusID:10034893 #http://arachne.uni-koeln.de/item/objekt/15946">mit einer Fackel</term>
      </nodes>
   </tag>
   <tag>
      <tag/>
      <facet>tei:term</facet>
      <link>http://arachne.uni-koeln.de/item/objekt/52889 http://arachne.uni-koeln.de/item/objekt/22200</link>
      <count>2</count>
      <nodes>
         <term xmlns="http://www.tei-c.org/ns/1.0"
               ref="#http://arachne.uni-koeln.de/item/objekt/52889 #http://arachne.uni-koeln.de/item/objekt/22200">25.</term>
      </nodes>
   </tag>
   <tag>
      <tag/>
      <facet>tei:term</facet>
      <link>http://arachne.uni-koeln.de/item/objekt/17963</link>
      <count>2</count>
      <nodes>
         <term xmlns="http://www.tei-c.org/ns/1.0"
               ref="#http://arachne.uni-koeln.de/item/objekt/17963">4.</term>
      </nodes>
   </tag>
   <tag>
      <tag>Palmerston, Henry Temple (vicomte)</tag>
      <facet>tei:term</facet>
      <link>http://arachne.uni-koeln.de/item/objekt/3029</link>
      <count>2</count>
      <nodes>
         <term xmlns="http://www.tei-c.org/ns/1.0"
               ref="#http://arachne.uni-koeln.de/item/objekt/3029">beym <term ref="#http://arachne.uni-koeln.de/item/sammlungen/1000005">
               <persName ref="#CerlID:cnp00548573" key="#PND:119151928">Milord Palmarton<addName type="display">Palmerston, Henry Temple (vicomte)</addName>
                  <addName>Henry Temple Palmerston</addName>
                  <addName>Henry Temple</addName>
                  <addName>Palmarton Milord</addName>
                  <addName>Palmarton</addName>
                  <addName>Temple, Henry vicomte Palmerston</addName>
                  <addName>Temple, Henry Viscount Palmerston</addName>
                  <addName>Temple Palmerston</addName>
               </persName>
            </term>
         </term>
      </nodes>
   </tag>
   <tag>
      <tag>Palmerston, Henry Temple (vicomte)</tag>
      <facet>tei:term</facet>
      <link>http://arachne.uni-koeln.de/item/sammlungen/1000005</link>
      <count>2</count>
      <nodes>
         <term xmlns="http://www.tei-c.org/ns/1.0"
               ref="#http://arachne.uni-koeln.de/item/sammlungen/1000005">
            <persName ref="#CerlID:cnp00548573" key="#PND:119151928">Milord Palmarton<addName type="display">Palmerston, Henry Temple (vicomte)</addName>
               <addName>Henry Temple Palmerston</addName>
               <addName>Henry Temple</addName>
               <addName>Palmarton Milord</addName>
               <addName>Palmarton</addName>
               <addName>Temple, Henry vicomte Palmerston</addName>
               <addName>Temple, Henry Viscount Palmerston</addName>
               <addName>Temple Palmerston</addName>
            </persName>
         </term>
      </nodes>
   </tag>
   <tag>
      <tag>Deutschland</tag>
      <facet>tei:term</facet>
      <link/>
      <count>2</count>
      <nodes>
         <term xmlns="http://www.tei-c.org/ns/1.0"
               ref="#placeholder-file:/home/ingop/repo/archaeo18/./content/app/tei-pages/weimar-hs-2056-172.tei.xml-d6081e177">sitzend, und in <placeName ref="#GettyID:7000084">Teutschland<addName type="display">Deutschland</addName>
               <addName>Deutschland</addName>
               <addName>Bundesrepublik Deutschland</addName>
               <addName>BRD</addName>
               <addName>Germany</addName>
               <addName>Federal Republic of Germany</addName>
               <addName>Allemagne</addName>
               <addName>République fédérale d'Allemagne</addName>
               <addName>República Federal de Alemania</addName>
               <addName>Alemania</addName>
               <addName>Alemanha</addName>
               <addName>Duitsland</addName>
               <addName>Germania</addName>
               <addName>DEU</addName>
               <addName>DE</addName>
               <addName>ISO276</addName>
               <addName>GM00</addName>
               <addName>Deutsches Reich</addName>
               <addName>ISO280</addName>
               <addName>German</addName>
            </placeName>
         </term>
      </nodes>
   </tag>
   <tag>
      <tag>Cavaceppi, Bartolomeo</tag>
      <facet>tei:term</facet>
      <link/>
      <count>2</count>
      <nodes>
         <term xmlns="http://www.tei-c.org/ns/1.0"
               ref="#placeholder-file:/home/ingop/repo/archaeo18/./content/app/tei-pages/weimar-hs-2056-172.tei.xml-d6081e231">Jst eine ganz neue von <persName ref="#CerlID:cnp00404698" key="#PND:119217597">Cavaceppi<addName type="display">Cavaceppi, Bartolomeo</addName>
               <addName>Bartolomeo Cavaceppi</addName>
            </persName>
         </term>
      </nodes>
   </tag>
   <tag>
      <tag>Villa Borghese</tag>
      <facet>tei:term</facet>
      <link>http://arachne.uni-koeln.de/item/objekt/14780 http://arachne.uni-koeln.de/item/objekt/36620 http://arachne.uni-koeln.de/item/objekt/36622</link>
      <count>2</count>
      <nodes>
         <term xmlns="http://www.tei-c.org/ns/1.0"
               ref="#http://arachne.uni-koeln.de/item/objekt/14780 #http://arachne.uni-koeln.de/item/objekt/36620 #http://arachne.uni-koeln.de/item/objekt/36622">Aus der <term ref="#http://arachne.uni-koeln.de/item/sammlungen/1000238">Villa Borghese</term> sind drey</term>
      </nodes>
   </tag>
   <tag>
      <tag/>
      <facet>tei:term</facet>
      <link>http://arachne.uni-koeln.de/item/sammlungen/1000238</link>
      <count>2</count>
      <nodes>
         <term xmlns="http://www.tei-c.org/ns/1.0"
               ref="#http://arachne.uni-koeln.de/item/sammlungen/1000238">Villa Borghese</term>
      </nodes>
   </tag>
   <tag>
      <tag/>
      <facet>tei:term</facet>
      <link>http://arachne.uni-koeln.de/item/objekt/29723 http://arachne.uni-koeln.de/item/objekt/26038</link>
      <count>2</count>
      <nodes>
         <term xmlns="http://www.tei-c.org/ns/1.0"
               ref="#http://arachne.uni-koeln.de/item/objekt/29723 #http://arachne.uni-koeln.de/item/objekt/26038">Noch 2 andere</term>
      </nodes>
   </tag>
   <tag>
      <tag/>
      <facet>tei:term</facet>
      <link>http://arachne.uni-koeln.de/item/objekt/18098</link>
      <count>2</count>
      <nodes>
         <term xmlns="http://www.tei-c.org/ns/1.0"
               ref="#http://arachne.uni-koeln.de/item/objekt/18098">29.</term>
      </nodes>
   </tag>
   <tag>
      <tag/>
      <facet>tei:term</facet>
      <link>http://arachne.uni-koeln.de/item/rezeption/300526</link>
      <count>2</count>
      <nodes>
         <term xmlns="http://www.tei-c.org/ns/1.0"
               ref="#http://arachne.uni-koeln.de/item/rezeption/300526">30.</term>
      </nodes>
   </tag>
   <tag>
      <tag/>
      <facet>tei:term</facet>
      <link>http://arachne.uni-koeln.de/item/objekt/13328</link>
      <count>2</count>
      <nodes>
         <term xmlns="http://www.tei-c.org/ns/1.0"
               ref="#http://arachne.uni-koeln.de/item/objekt/13328">32.</term>
      </nodes>
   </tag>
   <tag>
      <tag/>
      <facet>tei:term</facet>
      <link>http://arachne.uni-koeln.de/item/objekt/5336</link>
      <count>2</count>
      <nodes>
         <term xmlns="http://www.tei-c.org/ns/1.0"
               ref="#http://arachne.uni-koeln.de/item/objekt/5336">15.</term>
      </nodes>
   </tag>
   <tag>
      <tag/>
      <facet>tei:term</facet>
      <link>http://arachne.uni-koeln.de/item/objekt/52573</link>
      <count>2</count>
      <nodes>
         <term xmlns="http://www.tei-c.org/ns/1.0"
               ref="#http://arachne.uni-koeln.de/item/objekt/52573">66.</term>
      </nodes>
   </tag>
   <tag>
      <tag/>
      <facet>tei:term</facet>
      <link>http://arachne.uni-koeln.de/item/objekt/80290</link>
      <count>2</count>
      <nodes>
         <term xmlns="http://www.tei-c.org/ns/1.0"
               ref="#http://arachne.uni-koeln.de/item/objekt/80290">103.</term>
      </nodes>
   </tag>
   <tag>
      <tag>Palazzo di Duca Altemps</tag>
      <facet>tei:term</facet>
      <link>http://arachne.uni-koeln.de/item/objekt/36685</link>
      <count>2</count>
      <nodes>
         <term xmlns="http://www.tei-c.org/ns/1.0"
               ref="#http://arachne.uni-koeln.de/item/objekt/36685">Die im <term ref="#http://arachne.uni-koeln.de/item/sammlungen/1000343">Palazzo di Duca Altemps</term>
         </term>
      </nodes>
   </tag>
   <tag>
      <tag/>
      <facet>tei:term</facet>
      <link>http://arachne.uni-koeln.de/item/sammlungen/1000343</link>
      <count>2</count>
      <nodes>
         <term xmlns="http://www.tei-c.org/ns/1.0"
               ref="#http://arachne.uni-koeln.de/item/sammlungen/1000343">Palazzo di Duca Altemps</term>
      </nodes>
   </tag>
   <tag>
      <tag/>
      <facet>tei:term</facet>
      <link>http://arachne.uni-koeln.de/item/objekt/31559</link>
      <count>2</count>
      <nodes>
         <term xmlns="http://www.tei-c.org/ns/1.0"
               ref="#http://arachne.uni-koeln.de/item/objekt/31559">mit dem Cornu Copiæ und 
                            einen Apfel</term>
      </nodes>
   </tag>
   <tag>
      <tag/>
      <facet>tei:term</facet>
      <link/>
      <count>2</count>
      <nodes>
         <term xmlns="http://www.tei-c.org/ns/1.0"
               ref="#placeholder-file:/home/ingop/repo/archaeo18/./content/app/tei-pages/weimar-hs-2056-172.tei.xml-d6081e421">bey  
                                der</term>
      </nodes>
   </tag>
   <tag>
      <tag/>
      <facet>tei:term</facet>
      <link>http://arachne.uni-koeln.de/item/objekt/23539</link>
      <count>2</count>
      <nodes>
         <term xmlns="http://www.tei-c.org/ns/1.0"
               ref="#http://arachne.uni-koeln.de/item/objekt/23539">20.</term>
      </nodes>
   </tag>
   <tag>
      <tag/>
      <facet>tei:term</facet>
      <link>http://arachne.uni-koeln.de/item/objekt/5298</link>
      <count>2</count>
      <nodes>
         <term xmlns="http://www.tei-c.org/ns/1.0"
               ref="#http://arachne.uni-koeln.de/item/objekt/5298">63.</term>
      </nodes>
   </tag>
   <tag>
      <tag/>
      <facet>tei:term</facet>
      <link>http://arachne.uni-koeln.de/item/rezeption/300650</link>
      <count>2</count>
      <nodes>
         <term xmlns="http://www.tei-c.org/ns/1.0"
               ref="#http://arachne.uni-koeln.de/item/rezeption/300650">143.</term>
      </nodes>
   </tag>
   <tag>
      <tag/>
      <facet>tei:term</facet>
      <link>http://arachne.uni-koeln.de/item/objekt/28792</link>
      <count>2</count>
      <nodes>
         <term xmlns="http://www.tei-c.org/ns/1.0"
               ref="#http://arachne.uni-koeln.de/item/objekt/28792">144.</term>
      </nodes>
   </tag>
   <tag>
      <tag/>
      <facet>tei:term</facet>
      <link/>
      <count>2</count>
      <nodes>
         <term xmlns="http://www.tei-c.org/ns/1.0"
               ref="#placeholder-file:/home/ingop/repo/archaeo18/./content/app/tei-pages/weimar-hs-2056-172.tei.xml-d6081e495">Beym</term>
      </nodes>
   </tag>
</tags>
